Bluetin_Echo/Bluetin_Echo.py
Bluetin_Echo/__init__.py
Bluetin_Echo-0.2.0.dist-info/LICENSE
Bluetin_Echo-0.2.0.dist-info/METADATA
Bluetin_Echo-0.2.0.dist-info/WHEEL
Bluetin_Echo-0.2.0.dist-info/top_level.txt
Bluetin_Echo-0.2.0.dist-info/RECORD
