Metadata-Version: 2.1
Name: Bluetin-Echo
Version: 0.2.0
Summary: Raspberry Pi Python Library for Ultrasonic Module HC-SR04 Distance Measuring Transducer.
Home-page: https://github.com/MarkAHeywood/Bluetin_Python_Echo
Author: Mark A Heywood
Author-email: mark@shinex.com
License: MIT
Keywords: RPI,GPIO,Raspberry Pi,Ultrasonic,HC-SR04,Transducer,Distance Measuring,Sensor
Platform: UNKNOWN
Classifier: Development Status :: 4 - Beta
Classifier: Intended Audience :: Developers
Classifier: Intended Audience :: End Users/Desktop
Classifier: Intended Audience :: Science/Research
Classifier: Topic :: System :: Hardware
Classifier: Topic :: Home Automation
Classifier: Topic :: Software Development :: Libraries :: Python Modules
Classifier: License :: OSI Approved :: MIT License
Classifier: Programming Language :: Python :: 2.7
Classifier: Programming Language :: Python :: 3
Requires-Dist: RPi.GPIO
